docqa/__init__.py
docqa/config.py
docqa/document.py
docqa/pipeline.py
docqa/version.py
docqa/cmd/__init__.py
docqa/cmd/__main__.py
docqa/cmd/scan.py
docqa/ext/__init__.py
docqa/ext/model.py
docqa/ext/pipeline.py
docqa/ext/qa_helpers.py
docqa/ext/transformers.py
docqa-0.0.3.dist-info/LICENSE
docqa-0.0.3.dist-info/METADATA
docqa-0.0.3.dist-info/WHEEL
docqa-0.0.3.dist-info/entry_points.txt
docqa-0.0.3.dist-info/top_level.txt
docqa-0.0.3.dist-info/RECORD
